imas2xarray/__init__.py
imas2xarray/_io.py
imas2xarray/_lookup.py
imas2xarray/_models.py
imas2xarray/_rebase.py
imas2xarray/_utils.py
imas2xarray/data/__init__.py
imas2xarray/data/variables_core-profiles.yaml
imas2xarray/data/variables_core-sources.yaml
imas2xarray/data/variables_equilibrium.yaml
imas2xarray-0.4.0.dist-info/LICENSE
imas2xarray-0.4.0.dist-info/METADATA
imas2xarray-0.4.0.dist-info/WHEEL
imas2xarray-0.4.0.dist-info/top_level.txt
imas2xarray-0.4.0.dist-info/RECORD
