Metadata-Version: 2.1
Name: imas2xarray
Version: 0.4.0
Summary: Imas2xarray is a tool reading IMAS data in hdf5 format into xarray.
Author: Victor Azizi
Author-email: Stef Smeets <s.smeets@esciencecenter.nl>
License: Apache 2.0 License
Project-URL: homepage, https://github.com/duqtools/imas2xarray
Project-URL: issues, https://github.com/duqtools/imas2xarray/issues
Project-URL: documentation, https://imas2xarray.readthedocs.io
Project-URL: changelog, https://github.com/duqtools/imas2xarray/releases
Keywords: modelling,tokamak,fusion-reactor,imas
Classifier: Development Status :: 3 - Alpha
Classifier: Intended Audience :: Developers
Classifier: Intended Audience :: Science/Research
Classifier: License :: OSI Approved :: Apache Software License
Classifier: Natural Language :: English
Classifier: Operating System :: POSIX :: Linux
Classifier: Programming Language :: Python :: 3
Classifier: Programming Language :: Python :: 3.9
Classifier: Programming Language :: Python :: 3.10
Classifier: Programming Language :: Python :: 3.11
Classifier: Programming Language :: Python :: 3.12
Classifier: Topic :: Scientific/Engineering
Requires-Python: >=3.9
License-File: LICENSE
Requires-Dist: numpy
Requires-Dist: h5py
Requires-Dist: pydantic >=2.0
Requires-Dist: pydantic-yaml >=1.0
Requires-Dist: scipy
Requires-Dist: xarray
Requires-Dist: importlib-resources ; python_version < "3.10"
Provides-Extra: develop
Requires-Dist: bump-my-version ; extra == 'develop'
Requires-Dist: ruff ; extra == 'develop'
Requires-Dist: pre-commit ; extra == 'develop'
Requires-Dist: coverage[toml] ; extra == 'develop'
Requires-Dist: pytest ; extra == 'develop'
Requires-Dist: pytest-dependency ; extra == 'develop'
Requires-Dist: pycodestyle ; extra == 'develop'
Provides-Extra: docs
Requires-Dist: jinja2 ; extra == 'docs'
Requires-Dist: markdown-include ; extra == 'docs'
Requires-Dist: mkdocs ; extra == 'docs'
Requires-Dist: mkdocs-gen-files ; extra == 'docs'
Requires-Dist: mkdocs-material ; extra == 'docs'
Requires-Dist: mkdocstrings[python] ; extra == 'docs'
Requires-Dist: mknotebooks ; extra == 'docs'
Provides-Extra: imas
Requires-Dist: imas ; extra == 'imas'
Provides-Extra: publishing
Requires-Dist: twine ; extra == 'publishing'
Requires-Dist: wheel ; extra == 'publishing'
Requires-Dist: build ; extra == 'publishing'
